.gitignore
setup.py
dm/__init__.py
dm.zope.saml2.egg-info/PKG-INFO
dm.zope.saml2.egg-info/SOURCES.txt
dm.zope.saml2.egg-info/dependency_links.txt
dm.zope.saml2.egg-info/namespace_packages.txt
dm.zope.saml2.egg-info/not-zip-safe
dm.zope.saml2.egg-info/requires.txt
dm.zope.saml2.egg-info/top_level.txt
dm/zope/__init__.py
dm/zope/saml2/LICENSE.txt
dm/zope/saml2/README.txt
dm/zope/saml2/VERSION.txt
dm/zope/saml2/__init__.py
dm/zope/saml2/attribute.py
dm/zope/saml2/authority.py
dm/zope/saml2/configure.zcml
dm/zope/saml2/core.zcml
dm/zope/saml2/csrf.py
dm/zope/saml2/entity.py
dm/zope/saml2/exception.py
dm/zope/saml2/formlib.py
dm/zope/saml2/formlib.zcml
dm/zope/saml2/interfaces.py
dm/zope/saml2/permission.py
dm/zope/saml2/permission.zcml
dm/zope/saml2/role.py
dm/zope/saml2/sso.py
dm/zope/saml2/util.py
dm/zope/saml2/browser/__init__.py
dm/zope/saml2/browser/configure.zcml
dm/zope/saml2/browser/entity.py
dm/zope/saml2/browser/post.pt
dm/zope/saml2/browser/role.py
dm/zope/saml2/idpsso/__init__.py
dm/zope/saml2/idpsso/idpsso.py
dm/zope/saml2/spsso/__init__.py
dm/zope/saml2/spsso/configure.zcml
dm/zope/saml2/spsso/plugin.py
dm/zope/saml2/spsso/spsso.py
dm/zope/saml2/spsso/browser/__init__.py
dm/zope/saml2/spsso/browser/configure.zcml
dm/zope/saml2/spsso/browser/failure.py
dm/zope/saml2/spsso/browser/idp.py
dm/zope/saml2/tests/__init__.py
dm/zope/saml2/tests/test_authority.py
dm/zope/saml2/tests/test_idp.py
dm/zope/saml2/tests/resources/auth.cert
dm/zope/saml2/tests/resources/auth.key
dm/zope/saml2/tests/resources/feid.xml