Metadata-Version: 2.1
Name: dm.zope.saml2
Version: 5.1.0
Summary: Zope 2/Plone extension for SAML2 based Single Sign On: identity, attribute and service providers
Home-page: https://github.com/d-maurer/dm.zope.saml2
Author: Dieter Maurer
Author-email: dieter.maurer@online.de
License: ZPL
Keywords: application development zope saml2 sso plone
Classifier: Development Status :: 5 - Production/Stable
Classifier: Intended Audience :: Developers
Classifier: License :: OSI Approved :: GNU General Public License (GPL)
Classifier: Framework :: Zope
Classifier: Framework :: Zope :: 4
Classifier: Operating System :: OS Independent
Classifier: Programming Language :: Python
Classifier: Programming Language :: Python :: 2.7
Classifier: Programming Language :: Python :: 3
Classifier: Topic :: Utilities
Requires-Dist: dm.saml2>=3.2
Requires-Dist: dm.zope.schema>=4
Requires-Dist: five.formlib
Requires-Dist: decorator
Requires-Dist: setuptools
